[{"Lon":-113.500357621434,"Lat":53.6333358355386,"RemainingMyPropertyLookups":-1,"TAXROLLNUMBER":6982292,"MASTERTAXROLLNUMBER":6982292,"LANDUSEDESCRIPTION":null,"BUILDINGNAME":null,"MARKETBUILDINGCLASS":null,"PROPERTYTYPE":"RESIDENTIAL","EFFECTIVEBUILDYEAR":1979,"NETAREA":82.34,"BASEMENTFINISHED":null,"HASGARAGE":"N","HASFIREPLACE":null,"ASSESSEDVALUE":266500,"HOUSESUIT":null,"HOUSENUM":10220,"HOUSESUFF":null,"STREETNAME":"171A AVENUE NW","POSTALCODE":"T5X4L4","CITY":"EDMONTON","FULLADDRESS":"10220 171A AVENUE NW EDMONTON AB  ","NEIGHBOURHOOD":"BATURYN","FULLYTAXABLE":null,"FULLYCOMPLETE":null,"LOTSIZE":"315.744 M2 / 3398.6 FT2 / .078 AC","BUILDINGCOUNT":null,"BUILDYEARMBC":null,"WALKOUTBASEMENT":null,"AIRCONDITIONING":null,"VALUATION_GROUP":"RESIDENTIAL NORTH","DISPLAY_TYPE":"Residential","SITE_COVERAGE":null,"TOT_GROSS_AREA_DESCRIPTION":"82.34 M2 / 886.3 FT2","ACTUAL_ZONE":"RF1","ACTUAL_ZONE_DESC":"Single Detached Residential District","EFFECTIVE_ZONE":"RF1","EFFECTIVE_ZONE_DESC":"Single Detached Residential District","MAIL_DATE":"\/Date(1642143600000)\/","TAXABLE_STATUS":"January 1 - December 31, 2022; FULLY TAXABLE","ASSESSMENT_YEAR":2022,"LEGAL_DESCRIPTION":"Plan: 7920108  Block: 67  Lot: 34","GEOMETRY":"{\"type\": \"Polygon\",\"coordinates\":[[[33047, 5944643],[33037, 5944639],[33050, 5944611],[33059, 5944616],[33047, 5944643]]]}","RESULTCODE":1113,"RESULTMESSAGE":"Assessment found","RESULTDESCRIPTION":"An assessment record was found for the tax roll number."}]